autofeat/__init__.py
autofeat/autofeat.py
autofeat/autofeatlight.py
autofeat/feateng.py
autofeat/featsel.py
autofeat/nb_utils.py
autofeat-2.1.3.dist-info/LICENSE
autofeat-2.1.3.dist-info/METADATA
autofeat-2.1.3.dist-info/WHEEL
autofeat-2.1.3.dist-info/RECORD
